nonebot_plugin_auto_enter_group/__init__.py
nonebot_plugin_auto_enter_group/utils.py
nonebot_plugin_auto_enter_group-1.0.1.dist-info/METADATA
nonebot_plugin_auto_enter_group-1.0.1.dist-info/WHEEL
nonebot_plugin_auto_enter_group-1.0.1.dist-info/licenses/LICENSE
nonebot_plugin_auto_enter_group-1.0.1.dist-info/RECORD
