Metadata-Version: 2.4
Name: nonebot-plugin-auto-enter-group
Version: 1.0.1
Summary: NoneBot2 加群自动审批
License-File: LICENSE
Keywords: nonebot2,nonebot-plugin-auto-enter-group
Author: padoru233
Author-email: wr15624916906@gmail.com
Requires-Python: >=3.9
Classifier: Programming Language :: Python :: 3
Classifier: Programming Language :: Python :: 3.9
Classifier: Programming Language :: Python :: 3.10
Classifier: Programming Language :: Python :: 3.11
Classifier: Programming Language :: Python :: 3.12
Classifier: Programming Language :: Python :: 3.13
Classifier: Programming Language :: Python :: 3.14
Requires-Dist: nonebot-adapter-onebot (>=2.0.0,<3.0.0)
Requires-Dist: nonebot-plugin-localstore (>=0.7.1,<0.8.0)
Requires-Dist: nonebot2 (>=2.2.0)
Project-URL: Repository, https://github.com/padoru233/nonebot-plugin-auto-enter-group
